<?xml version="1.0" encoding="utf-8"?>

<CODE-OBJECTS>

<jPlaton version="2_8j"></jPlaton>
<Application code="bo-system" name="database226" key="2fbd92c88106dc26c55797d7f29f01bf"></Application>
<Developer code="1" name="B-open" key="3478403624e74e4cf44ca4a78bda74fe"></Developer>
<Source date="2015-06-15" time="12:49:27" key="dd43b58da2a652976095f5d0349bd29e"></Source>

     <DEFINITIONS>

         <procedure1 type="Procedure"></procedure1>
         <procedure2 type="Procedure"></procedure2>
         <procedure3 type="Procedure"></procedure3>
         <setProperties type="Procedure"></setProperties>

     </DEFINITIONS>

     <PROPERTIES>

        <s_procedure1
            action_type="after_unit_open"
        ></s_procedure1>
        <s_procedure2
            action_type="s_DataForm1.on_submit"
        ></s_procedure2>
        <s_setProperties
            action_type="after_unit_open"
         ></s_setProperties>

     </PROPERTIES>

     <SOURCES>

        <s_procedure1>
            <![CDATA[START:s_procedure1
	DOCTYPE <!DOCTYPE HTML PUBLIC "-//W3C//DTD HTML 4.01 Transitional//EN" "http://www.w3.org/TR/html4/loose.dtd">
	PROPERTY this table.columns 1
	PROPERTY this table.rows 1
	PROPERTY this table.centered false
	PROPERTY this table.border 0
	PROPERTY this table.width 100%
	PROPERTY this table.tdwidth 4%
	PROPERTY this table.cellpadding 0
	PROPERTY this table.className newback2
	PROPERTY this table.classNameie newback2
	PROPERTY this td1.overflow visible
	PROPERTY this td1.indivheight 100%
  RETURN 1																	            ]]>
        </s_procedure1>

        <s_procedure2>
            <![CDATA[START:s_procedure2


CALL s_procedure3

	HTML
		<div class='formContainer'>
			<div class='rightBlockContainer'>
				<div class='formRow'>
					<span class='formRowLabel'>#s_Record1.TEST3.BOOK_TITLE label#</span>
					<span class='formRowValue'>#s_Record1.TEST3.BOOK_TITLE#</span>
				</div>
				<div class='formRow'>
					<span class='formRowLabel'>#s_Record1.TEST3.AUTHOR_NAME label#</span>
					<span class='formRowValue'>#s_Record1.TEST3.AUTHOR_NAME#</span>
				</div>
				<div class='formRow'>
					<span class='formRowLabel'>#s_Record1.TEST3.EDITION label#</span>
					<span class='formRowValue'>#s_Record1.TEST3.EDITION#</span>
				</div>
				<div class='formRow'>
					<span class='formRowLabel'>#s_Record1.TEST3.YEAR label#</span>
					<span class='formRowValue'>#s_Record1.TEST3.YEAR#</span>
				</div>
				<div class='formRow'>
					<span class='formRowLabel'>#s_Record1.TEST3.ISSN_ISBN label#</span>
					<span class='formRowValue'>#s_Record1.TEST3.ISSN_ISBN#</span>
				</div>
				<div class='formRow'>
					<span class='formRowLabel'>#s_Record1.TEST3.LIBRARY_ID label#</span>
					<span class='formRowValue'>#s_Record1.TEST3.LIBRARY_ID#</span>
				</div>
				<div class='formRow'>
					<span class='formRowLabel'>#s_Record1.TEST3.LOST label#</span>
					<span class='formRowValue'>#s_Record1.TEST3.LOST#</span>
				</div>
				<div class='formRow'>
					<span class='formRowLabel'>#s_Record1.TEST3.HOLD label#</span>
					<span class='formRowValue'>#s_Record1.TEST3.HOLD#</span>
				</div>

        </div>		</div>
		
	ENDHTML
  RETURN 1																	            ]]>
        </s_procedure2>

        <s_procedure3>
            <![CDATA[START:s_procedure3

       

 @VAR:INTEGER
       
 @VAR=0
       
 ACTION s_DataSet1 EXECUTE     
        
first s_DataSet1 
       

 LOOP
          
  IF (#VALUE#<=0)
              
  BREAK
 
            
          
  @VAR=@VAR+1   
            
   

         next s_DataSet1
      
 ENDLOOP
        
       
 
HTML
               

 <div>
                 

   <script>
                      

  function myFunction1() {
                 

       alert("TREXEI");
               
         }
                   

 </script>
		      
  </div>
		        
	
	        <div>
                 
   <script>
                      
                      g=document.createElement('div'); g.setAttribute("id", "Div1");
                      
 function myFunction() {
    int test = document.getElementById("id").value;
      alert("TA RECORDS EINAI "+@VAR);
   
                     }
                 
   </script>
		        
</div>

ENDHTML


RETURN 1    
                        
                                                                                                                                                                                                                                                                                                                                                                                           

            ]]>
        </s_procedure3>

        <s_setProperties>
            <![CDATA[START:s_setProperties

	DOCTYPE <!DOCTYPE HTML PUBLIC "-//W3C//DTD HTML 4.01 Transitional//EN" "http://www.w3.org/TR/html4/loose.dtd">
	PROPERTY this table.columns 1
	PROPERTY this table.rows 1
	PROPERTY this table.border 0
	PROPERTY this table.layout fixed
	PROPERTY this table.width 100%
	PROPERTY this table.tdwidth 4%
	PROPERTY this table.cellpadding 0
	PROPERTY this table.className newback2
	PROPERTY this table.classNameie newback2
	PROPERTY this td1.overflow visible
	PROPERTY this td1.indivheight 100%

	RETURN 1
            ]]>
        </s_setProperties>

     </SOURCES>

</CODE-OBJECTS>
